README
emojencode.py
setup.py
emojencode.egg-info/PKG-INFO
emojencode.egg-info/SOURCES.txt
emojencode.egg-info/dependency_links.txt
emojencode.egg-info/entry_points.txt
emojencode.egg-info/top_level.txt