Metadata-Version: 1.0
Name: emojencode
Version: 1.2
Summary: Encode binary data as emoji! 😄
Home-page: https://github.com/doctaphred/emojencode
Author: Frederick "doctaphred" Wagner
Author-email: yo@doctaph.red
License: UNKNOWN
Platform: UNKNOWN
